podiff2/__init__.py
podiff2/podiff.py
podiff2-0.0.1.dist-info/LICENSE
podiff2-0.0.1.dist-info/METADATA
podiff2-0.0.1.dist-info/WHEEL
podiff2-0.0.1.dist-info/entry_points.txt
podiff2-0.0.1.dist-info/top_level.txt
podiff2-0.0.1.dist-info/RECORD
