Metadata-Version: 2.1
Name: podiff2
Version: 0.0.1
Summary: compare two .po/gettext files for differences 
Home-page: https://github.com/eshagh79/podiff2
Author: eshagh
Author-email: eshagh094@gmail.com
License: UNKNOWN
Project-URL: Bug Tracker, https://github.com/eshagh79/podiff2/issues
Keywords: po gettext compare diff
Platform: UNKNOWN
Classifier: Programming Language :: Python :: 3
Classifier: License :: OSI Approved :: GNU General Public License v3 or later (GPLv3+)
Classifier: Operating System :: OS Independent
Requires-Python: >=3.6
Requires-Dist: polib
